research/__init__.py
visdatcompy/__init__.py
visdatcompy/feature_extractor.py
visdatcompy/hash.py
visdatcompy/image_handler.py
visdatcompy/metrics.py
visdatcompy/utils.py
visdatcompy/visdatcompare.py
visdatcompy-0.8.4.dist-info/LICENSE
visdatcompy-0.8.4.dist-info/METADATA
visdatcompy-0.8.4.dist-info/WHEEL
visdatcompy-0.8.4.dist-info/top_level.txt
visdatcompy-0.8.4.dist-info/RECORD
