Metadata-Version: 2.1
Name: visdatcompy
Version: 0.8.4
Summary: Библиотека для сравнения визуальных наборов данных
Home-page: https://github.com/cloudysock/visdatcompy
Author: cls, Reape4er, Adg1r
Author-email: ferjenkill@gmail.com
Requires-Python: >=3.12
License-File: LICENSE
Requires-Dist: pillow >=10.2.0
Requires-Dist: scikit-image >=0.22.0
Requires-Dist: scikit-learn >=1.4.0
Requires-Dist: numpy >=1.26.2
Requires-Dist: pandas >=2.1.4
Requires-Dist: colorama >=0.4.6
Requires-Dist: opencv-contrib-python >=4.9.0.80
Requires-Dist: scipy >=1.12.0
Requires-Dist: matplotlib >=3.8.2
Requires-Dist: ipywidgets >=8.1.2
